edftpy/__init__.py
edftpy/__main__.py
edftpy/evaluator.py
edftpy/interface.py
edftpy/optimizer.py
edftpy/api/__init__.py
edftpy/api/api4ase.py
edftpy/api/dftd4.py
edftpy/api/parse_config.py
edftpy/config/__init__.py
edftpy/config/config.py
edftpy/config/configentries.json
edftpy/cui/__init__.py
edftpy/cui/convert.py
edftpy/cui/main.py
edftpy/cui/run.py
edftpy/density/__init__.py
edftpy/density/density.py
edftpy/engine/__init__.py
edftpy/engine/driver.py
edftpy/engine/engine.py
edftpy/engine/engine_castep.py
edftpy/engine/engine_dftpy.py
edftpy/engine/engine_environ.py
edftpy/engine/engine_mbx.py
edftpy/engine/engine_qe.py
edftpy/engine/hamiltonian.py
edftpy/engine/old/ks_castep.py
edftpy/engine/old/ks_dftpy.py
edftpy/functional/__init__.py
edftpy/functional/embedding.py
edftpy/functional/functionals.py
edftpy/functional/hartree.py
edftpy/functional/pseudopotential.py
edftpy/functional/xc.py
edftpy/functional/kedf/__init__.py
edftpy/functional/kedf/revhc.py
edftpy/io/__init__.py
edftpy/mixer/__init__.py
edftpy/mpi/__init__.py
edftpy/mpi/mpi.py
edftpy/mpi/utils.py
edftpy/properties/__init__.py
edftpy/properties/density.py
edftpy/properties/force.py
edftpy/properties/perturbation.py
edftpy/properties/potential.py
edftpy/subsystem/__init__.py
edftpy/subsystem/decompose.py
edftpy/subsystem/subcell.py
edftpy/tddft/__init__.py
edftpy/tddft/optical.py
edftpy/utils/__init__.py
edftpy/utils/common.py
edftpy/utils/math.py
edftpy/utils/occupations.py
edftpy-0.0.1rc0.data/scripts/edftpy
edftpy-0.0.1rc0.dist-info/LICENSE.txt
edftpy-0.0.1rc0.dist-info/METADATA
edftpy-0.0.1rc0.dist-info/WHEEL
edftpy-0.0.1rc0.dist-info/top_level.txt
edftpy-0.0.1rc0.dist-info/RECORD
