Metadata-Version: 2.1
Name: edftpy
Version: 0.0.1rc0
Summary: Density Embedding Scheme with Python
Home-page: https://gitlab.com/pavanello-research-group/edftpy
Author: Pavanello Research Group
Author-email: m.pavanello@rutgers.edu
License: MIT
Platform: UNKNOWN
Classifier: Development Status :: 3 - Alpha
Classifier: Intended Audience :: Science/Research
Classifier: License :: OSI Approved :: MIT License
Classifier: Programming Language :: Python :: 3
Classifier: Programming Language :: Python :: 3.6
Classifier: Programming Language :: Python :: 3.7
Classifier: Programming Language :: Python :: 3.8
Classifier: Programming Language :: Python :: 3.9
Classifier: Programming Language :: Python :: 3.10
Classifier: Topic :: Scientific/Engineering :: Chemistry
Classifier: Topic :: Scientific/Engineering :: Physics
License-File: LICENSE.txt
Requires-Dist: dftpy (>=2.0.3)
Requires-Dist: mpi4py (>=3.0.2)
Requires-Dist: mpi4py-fft (>=2.0.3)
Provides-Extra: all
Requires-Dist: pyfftw ; extra == 'all'
Provides-Extra: libxc
Requires-Dist: pylibxc2 ; (python_version < "3.10") and extra == 'libxc'
